README.md
setup.py
gensqlalorm/__init__.py
gensqlalorm/__main__.py
gensqlalorm.egg-info/PKG-INFO
gensqlalorm.egg-info/SOURCES.txt
gensqlalorm.egg-info/dependency_links.txt
gensqlalorm.egg-info/entry_points.txt
gensqlalorm.egg-info/requires.txt
gensqlalorm.egg-info/top_level.txt
gensqlalorm.egg-info/zip-safe
gensqlalorm/config/__init__.py
gensqlalorm/db/__init__.py
gensqlalorm/db/db_analysis.py
gensqlalorm/db/db_connect.py
gensqlalorm/db/db_executor.py
gensqlalorm/gen/__init__.py
gensqlalorm/gen/gen_mapper.py
gensqlalorm/gen/gen_orm_model.py
gensqlalorm/gen/gen_table_model.py
gensqlalorm/generate/__init__.py
gensqlalorm/utils/__init__.py
gensqlalorm/utils/file_utils.py
gensqlalorm/utils/string_utils.py